PythonFenbushijisuan/README.md
PythonFenbushijisuan/__init__.py
PythonFenbushijisuan/__main__.py
PythonFenbushijisuan/file.epub
PythonFenbushijisuan/index.html
PythonFenbushijisuan/css/__init__.py
PythonFenbushijisuan/css/annotations.css
PythonFenbushijisuan/css/main.css
PythonFenbushijisuan/css/normalize.css
PythonFenbushijisuan/css/popup.css
PythonFenbushijisuan/font/__init__.py
PythonFenbushijisuan/font/fontello.eot
PythonFenbushijisuan/font/fontello.svg
PythonFenbushijisuan/font/fontello.ttf
PythonFenbushijisuan/font/fontello.woff
PythonFenbushijisuan/img/__init__.py
PythonFenbushijisuan/img/annotator-glyph-sprite.png
PythonFenbushijisuan/img/annotator-icon-sprite.png
PythonFenbushijisuan/img/apple-touch-icon.png
PythonFenbushijisuan/img/cancelfullscreen.png
PythonFenbushijisuan/img/close.png
PythonFenbushijisuan/img/fullscreen.png
PythonFenbushijisuan/img/loader.gif
PythonFenbushijisuan/img/menu-icon.png
PythonFenbushijisuan/img/save.png
PythonFenbushijisuan/img/saved.png
PythonFenbushijisuan/img/settings-s.png
PythonFenbushijisuan/img/settings.png
PythonFenbushijisuan/img/star.png
PythonFenbushijisuan/js/__init__.py
PythonFenbushijisuan/js/epub.js
PythonFenbushijisuan/js/epub.min.js
PythonFenbushijisuan/js/epub.min.map
PythonFenbushijisuan/js/hooks.min.js
PythonFenbushijisuan/js/hooks.min.map
PythonFenbushijisuan/js/reader.js
PythonFenbushijisuan/js/reader.js.map
PythonFenbushijisuan/js/reader.min.js
PythonFenbushijisuan/js/reader.min.map
PythonFenbushijisuan/js/hooks/__init__.py
PythonFenbushijisuan/js/hooks/extensions/__init__.py
PythonFenbushijisuan/js/hooks/extensions/highlight.js
PythonFenbushijisuan/js/libs/__init__.py
PythonFenbushijisuan/js/libs/jquery.min.js
PythonFenbushijisuan/js/libs/localforage.min.js
PythonFenbushijisuan/js/libs/screenfull.js
PythonFenbushijisuan/js/libs/screenfull.min.js
PythonFenbushijisuan/js/libs/zip.min.js
PythonFenbushijisuan/js/plugins/__init__.py
PythonFenbushijisuan/js/plugins/hypothesis.js
python_fenbushijisuan-2024.3.4.0.dist-info/METADATA
python_fenbushijisuan-2024.3.4.0.dist-info/WHEEL
python_fenbushijisuan-2024.3.4.0.dist-info/entry_points.txt
python_fenbushijisuan-2024.3.4.0.dist-info/top_level.txt
python_fenbushijisuan-2024.3.4.0.dist-info/RECORD
